enhancementkit/__init__.py
enhancementkit/codeformer.py
enhancementkit/realesrgan.py
enhancementkit/utils.py
enhancementkit/nets/__init__.py
enhancementkit/nets/codeformer.py
enhancementkit/nets/vqgan.py
enhancementkit-0.2.dist-info/METADATA
enhancementkit-0.2.dist-info/WHEEL
enhancementkit-0.2.dist-info/top_level.txt
enhancementkit-0.2.dist-info/RECORD
